<?xml version="1.0" encoding="UTF-8"?>
<objects serializationModel="Studio.02.00.00">
	<object class="AudioFile" id="{b266ca1a-3ee4-4c9d-8c4f-8ae8e89f68d5}">
		<property name="assetPath">
			<value>FOLEY_jump_concrete_10.wav</value>
		</property>
		<property name="frequencyInKHz">
			<value>44.0999985</value>
		</property>
		<property name="channelCount">
			<value>1</value>
		</property>
		<property name="length">
			<value>0.45000000000000001</value>
		</property>
		<relationship name="masterAssetFolder">
			<destination>{a2ec2d88-4c6d-4ac0-99f5-1697813b95fd}</destination>
		</relationship>
	</object>
</objects>
